glmpca/__init__.py
glmpca/glmpca.py
tests/__init__.py
tests/glmpca_tests.py
glmpca-0.1.0.dist-info/LICENSE
glmpca-0.1.0.dist-info/METADATA
glmpca-0.1.0.dist-info/WHEEL
glmpca-0.1.0.dist-info/top_level.txt
glmpca-0.1.0.dist-info/RECORD
