Metadata-Version: 2.1
Name: glmpca
Version: 0.1.0
Summary: Generalized PCA for dimension reduction of non-normally distributed data
Home-page: https://github.com/willtownes/glmpca-py
Author: Will Townes
Author-email: will.townes@gmail.com
License: UNKNOWN
Platform: UNKNOWN
Classifier: Programming Language :: Python :: 3
Classifier: License :: OSI Approved :: GNU Lesser General Public License v3 or later (LGPLv3+)
Classifier: Operating System :: OS Independent
Classifier: Development Status :: 3 - Alpha
Classifier: Intended Audience :: Science/Research
Classifier: Topic :: Scientific/Engineering
Classifier: Topic :: Scientific/Engineering :: Bio-Informatics
Requires-Python: >=3.5
